<?xml version="1.0" encoding="UTF-8"?>
<!DOCTYPE suppressions PUBLIC "-//Puppy Crawl//DTD Suppressions 1.1//EN" "http://www.puppycrawl.com/dtds/suppressions_1_1.dtd">

<!--
SPDX-License-Identifier: Apache-2.0 OR MIT

SPDX-FileCopyrightText: Copyright 2021 Micron Technology, Inc.
-->

<suppressions>
  <suppress files="[\\/]src[\\/]test[\\/].*" checks="AvoidStaticImport" />
  <suppress files="[\\/]src[\\/]test[\\/].*" checks="EmptyBlock" />
  <suppress files="[\\/]src[\\/]test[\\/].*" checks="JavadocPackage" />
  <suppress files="[\\/]src[\\/]test[\\/].*" checks="JavadocVariable" />
  <suppress files="[\\/]src[\\/]test[\\/].*" checks="MagicNumber" />
  <suppress files="[\\/]src[\\/]test[\\/].*" checks="MethodName" />
  <suppress files="[\\/]src[\\/]test[\\/].*" checks="MissingJavadocMethod" />
  <suppress files="[\\/]src[\\/]test[\\/].*" checks="MissingJavadocType" />
  <suppress files="[\\/]src[\\/]test[\\/].*" checks="MultipleStringLiterals" />
  <suppress files="[\\/]src[\\/]test[\\/].*" checks="WriteTag" />
</suppressions>
